{
  "homographies": {
    "1": [
      [
        0.03487772561430568,
        0.051750274674067634,
        3.900722159678344
      ],
      [
        0.0005245465301535148,
        -0.14023810115591356,
        55.783140098094535
      ],
      [
        7.177653390724766e-05,
        0.0014663623722998788,
        0.9999999999999999
      ]
    ],
    "2": [
      [
        -0.030710178067327402,
        0.05197702615979722,
        64.0307503951475
      ],
      [
        -0.00026589662293757224,
        0.13330163874647194,
        -53.1864342307529
      ],
      [
        -1.8148724336320466e-05,
        0.0014679381698908581,
        1.0
      ]
    ],
    "3": [
      [
        0.028000854523034586,
        2.92994916279678e-05,
        -26.476927151967885
      ],
      [
        -0.00030611076628690823,
        -0.12793992531261789,
        51.70736556360602
      ],
      [
        -1.3357152884420328e-06,
        0.0013118102678557127,
        1.0
      ]
    ],
    "4": [
      [
        -0.028027911927370898,
        -0.0007878512504874384,
        27.084788188863428
      ],
      [
        0.00015126008768599113,
        0.12448833682557277,
        -50.64775531462179
      ],
      [
        -3.1338210354550083e-07,
        0.0012588023287794584,
        1.0
      ]
    ],
    "5": [
      [
        0.028473386173465332,
        -0.04634326975149063,
        -63.37345616020338
      ],
      [
        -9.200727708392182e-05,
        -0.1294645024050692,
        52.201433584195165
      ],
      [
        1.5592317551404523e-05,
        0.001332617576561472,
        0.9999999999999999
      ]
    ],
    "6": [
      [
        -0.03310725800497133,
        -0.05879569075964642,
        -3.5104457426962243
      ],
      [
        -0.0005789643001926563,
        0.1444094606240331,
        -57.172391865676474
      ],
      [
        2.3971523760561666e-05,
        0.0016395773777489247,
        1.0
      ]
    ]
  },
  "camera_calibrations": {
    "1": {
      "camera_id": 1,
      "image_path": "/ssd/ISSIA-Soccer/Annotation/Reference-Camera-1.bmp",
      "field_length_m": 105.0,
      "field_width_m": 68.0,
      "world_coordinate_system": {
        "origin": "field_center",
        "x_axis": "east_positive_long_axis",
        "y_axis": "north_positive_short_axis",
        "units": "meters"
      },
      "image_points": {
        "NE_CORNER": [
          1646.3999999999999,
          98.39999999999999
        ],
        "EAST_PENALTY_NW": [
          994.8,
          205.2
        ],
        "EAST_PENALTY_NE": [
          1725.6,
          199.2
        ],
        "EAST_PENALTY_SW": [
          1024.8,
          706.8
        ],
        "EAST_GOAL_AREA_NW": [
          1537.1999999999998,
          302.4
        ],
        "EAST_GOAL_AREA_NE": [
          1804.8,
          301.2
        ],
        "EAST_GOAL_AREA_SW": [
          1652.3999999999999,
          524.4
        ],
        "EAST_PENALTY_SPOT": [
          1292.3999999999999,
          399.59999999999997
        ],
        "EAST_GOAL_CENTER": [
          1885.1999999999998,
          409.2
        ]
      },
      "world_points": {
        "NE_CORNER": [
          52.5,
          34.0
        ],
        "EAST_PENALTY_NW": [
          36.0,
          20.16
        ],
        "EAST_PENALTY_NE": [
          52.5,
          20.16
        ],
        "EAST_PENALTY_SW": [
          36.0,
          -20.16
        ],
        "EAST_GOAL_AREA_NW": [
          47.0,
          9.16
        ],
        "EAST_GOAL_AREA_NE": [
          52.5,
          9.16
        ],
        "EAST_GOAL_AREA_SW": [
          47.0,
          -9.16
        ],
        "EAST_PENALTY_SPOT": [
          41.5,
          0.0
        ],
        "EAST_GOAL_CENTER": [
          52.5,
          0.0
        ]
      },
      "homography_image_to_world": [
        [
          0.03487772561430568,
          0.051750274674067634,
          3.900722159678344
        ],
        [
          0.0005245465301535148,
          -0.14023810115591356,
          55.783140098094535
        ],
        [
          7.177653390724766e-05,
          0.0014663623722998788,
          0.9999999999999999
        ]
      ],
      "reprojection_errors_m": {
        "NE_CORNER": 0.12379578764783083,
        "EAST_PENALTY_NW": 0.1688928129439034,
        "EAST_PENALTY_NE": 0.15168400730858553,
        "EAST_PENALTY_SW": 0.17545229101915108,
        "EAST_GOAL_AREA_NW": 0.09419834499074026,
        "EAST_GOAL_AREA_NE": 0.07091931618382745,
        "EAST_GOAL_AREA_SW": 0.21278951272885296,
        "EAST_PENALTY_SPOT": 0.2514167560660266,
        "EAST_GOAL_CENTER": 0.3879420137868395
      },
      "reprojection_rmse_m": 0.20290484070306408
    },
    "2": {
      "camera_id": 2,
      "image_path": "/ssd/ISSIA-Soccer/Annotation/Reference-Camera-2.bmp",
      "field_length_m": 105.0,
      "field_width_m": 68.0,
      "world_coordinate_system": {
        "origin": "field_center",
        "x_axis": "east_positive_long_axis",
        "y_axis": "north_positive_short_axis",
        "units": "meters"
      },
      "image_points": {
        "SE_CORNER": [
          295.2,
          106.8
        ],
        "EAST_PENALTY_NW": [
          903.5999999999999,
          706.8
        ],
        "EAST_PENALTY_SE": [
          214.79999999999998,
          201.6
        ],
        "EAST_PENALTY_SW": [
          930.0,
          206.39999999999998
        ],
        "EAST_GOAL_AREA_NW": [
          277.2,
          522.0
        ],
        "EAST_GOAL_AREA_SE": [
          133.2,
          302.4
        ],
        "EAST_GOAL_AREA_SW": [
          396.0,
          302.4
        ],
        "EAST_PENALTY_SPOT": [
          636.0,
          398.4
        ],
        "EAST_GOAL_CENTER": [
          56.4,
          397.2
        ]
      },
      "world_points": {
        "SE_CORNER": [
          52.5,
          -34.0
        ],
        "EAST_PENALTY_NW": [
          36.0,
          20.16
        ],
        "EAST_PENALTY_SE": [
          52.5,
          -20.16
        ],
        "EAST_PENALTY_SW": [
          36.0,
          -20.16
        ],
        "EAST_GOAL_AREA_NW": [
          47.0,
          9.16
        ],
        "EAST_GOAL_AREA_SE": [
          52.5,
          -9.16
        ],
        "EAST_GOAL_AREA_SW": [
          47.0,
          -9.16
        ],
        "EAST_PENALTY_SPOT": [
          41.5,
          0.0
        ],
        "EAST_GOAL_CENTER": [
          52.5,
          0.0
        ]
      },
      "homography_image_to_world": [
        [
          -0.030710178067327402,
          0.05197702615979722,
          64.0307503951475
        ],
        [
          -0.00026589662293757224,
          0.13330163874647194,
          -53.1864342307529
        ],
        [
          -1.8148724336320466e-05,
          0.0014679381698908581,
          1.0
        ]
      ],
      "reprojection_errors_m": {
        "SE_CORNER": 0.11920718046781792,
        "EAST_PENALTY_NW": 0.1292492242581584,
        "EAST_PENALTY_SE": 0.2572808210741625,
        "EAST_PENALTY_SW": 0.07906812439795373,
        "EAST_GOAL_AREA_NW": 0.13028999869951718,
        "EAST_GOAL_AREA_SE": 0.20345160664425213,
        "EAST_GOAL_AREA_SW": 0.1317837041405402,
        "EAST_PENALTY_SPOT": 0.16664664693131465,
        "EAST_GOAL_CENTER": 0.17578769061776675
      },
      "reprojection_rmse_m": 0.16253830482732207
    },
    "3": {
      "camera_id": 3,
      "image_path": "/ssd/ISSIA-Soccer/Annotation/Reference-Camera-3.bmp",
      "field_length_m": 105.0,
      "field_width_m": 68.0,
      "world_coordinate_system": {
        "origin": "field_center",
        "x_axis": "east_positive_long_axis",
        "y_axis": "north_positive_short_axis",
        "units": "meters"
      },
      "image_points": {
        "CENTER": [
          945.5999999999999,
          398.4
        ],
        "HALF_NORTH": [
          945.5999999999999,
          100.8
        ],
        "HALF_SOUTH": [
          945.5999999999999,
          1026.0
        ],
        "CENTER_CIRCLE_NORTH": [
          945.5999999999999,
          304.8
        ],
        "CENTER_CIRCLE_SOUTH": [
          943.1999999999999,
          519.6
        ],
        "CENTER_CIRCLE_WEST": [
          445.2,
          404.4
        ],
        "CENTER_CIRCLE_EAST": [
          1443.6,
          402.0
        ]
      },
      "world_points": {
        "CENTER": [
          0.0,
          0.0
        ],
        "HALF_NORTH": [
          0.0,
          34.0
        ],
        "HALF_SOUTH": [
          0.0,
          -34.0
        ],
        "CENTER_CIRCLE_NORTH": [
          0.0,
          9.15
        ],
        "CENTER_CIRCLE_SOUTH": [
          0.0,
          -9.15
        ],
        "CENTER_CIRCLE_WEST": [
          -9.15,
          0.0
        ],
        "CENTER_CIRCLE_EAST": [
          9.15,
          0.0
        ]
      },
      "homography_image_to_world": [
        [
          0.028000854523034586,
          2.92994916279678e-05,
          -26.476927151967885
        ],
        [
          -0.00030611076628690823,
          -0.12793992531261789,
          51.70736556360602
        ],
        [
          -1.3357152884420328e-06,
          0.0013118102678557127,
          1.0
        ]
      ],
      "reprojection_errors_m": {
        "CENTER": 0.2936919342083638,
        "HALF_NORTH": 0.06080324052259949,
        "HALF_SOUTH": 0.05706188067838065,
        "CENTER_CIRCLE_NORTH": 0.2683314182800966,
        "CENTER_CIRCLE_SOUTH": 0.1907056398711352,
        "CENTER_CIRCLE_WEST": 0.10969431739831863,
        "CENTER_CIRCLE_EAST": 0.10907648857913095
      },
      "reprojection_rmse_m": 0.17948695107713317
    },
    "4": {
      "camera_id": 4,
      "image_path": "/ssd/ISSIA-Soccer/Annotation/Reference-Camera-4.bmp",
      "field_length_m": 105.0,
      "field_width_m": 68.0,
      "world_coordinate_system": {
        "origin": "field_center",
        "x_axis": "east_positive_long_axis",
        "y_axis": "north_positive_short_axis",
        "units": "meters"
      },
      "image_points": {
        "CENTER": [
          955.1999999999999,
          402.0
        ],
        "HALF_NORTH": [
          937.1999999999999,
          1035.6
        ],
        "HALF_SOUTH": [
          963.5999999999999,
          98.39999999999999
        ],
        "CENTER_CIRCLE_NORTH": [
          951.5999999999999,
          525.6
        ],
        "CENTER_CIRCLE_SOUTH": [
          957.5999999999999,
          306.0
        ],
        "CENTER_CIRCLE_WEST": [
          1448.3999999999999,
          406.79999999999995
        ],
        "CENTER_CIRCLE_EAST": [
          460.79999999999995,
          408.0
        ]
      },
      "world_points": {
        "CENTER": [
          0.0,
          0.0
        ],
        "HALF_NORTH": [
          0.0,
          34.0
        ],
        "HALF_SOUTH": [
          0.0,
          -34.0
        ],
        "CENTER_CIRCLE_NORTH": [
          0.0,
          9.15
        ],
        "CENTER_CIRCLE_SOUTH": [
          0.0,
          -9.15
        ],
        "CENTER_CIRCLE_WEST": [
          -9.15,
          0.0
        ],
        "CENTER_CIRCLE_EAST": [
          9.15,
          0.0
        ]
      },
      "homography_image_to_world": [
        [
          -0.028027911927370898,
          -0.0007878512504874384,
          27.084788188863428
        ],
        [
          0.00015126008768599113,
          0.12448833682557277,
          -50.64775531462179
        ],
        [
          -3.1338210354550083e-07,
          0.0012588023287794584,
          1.0
        ]
      ],
      "reprojection_errors_m": {
        "CENTER": 0.30481998330398885,
        "HALF_NORTH": 0.043930423719364405,
        "HALF_SOUTH": 0.0455413732281427,
        "CENTER_CIRCLE_NORTH": 0.16486870436104203,
        "CENTER_CIRCLE_SOUTH": 0.1894228428650182,
        "CENTER_CIRCLE_WEST": 0.1410303195420962,
        "CENTER_CIRCLE_EAST": 0.140861735492716
      },
      "reprojection_rmse_m": 0.16890969846892054
    },
    "5": {
      "camera_id": 5,
      "image_path": "/ssd/ISSIA-Soccer/Annotation/Reference-Camera-5.bmp",
      "field_length_m": 105.0,
      "field_width_m": 68.0,
      "world_coordinate_system": {
        "origin": "field_center",
        "x_axis": "east_positive_long_axis",
        "y_axis": "north_positive_short_axis",
        "units": "meters"
      },
      "image_points": {
        "NW_CORNER": [
          285.59999999999997,
          103.19999999999999
        ],
        "WEST_PENALTY_NW": [
          206.39999999999998,
          204.0
        ],
        "WEST_PENALTY_NE": [
          933.5999999999999,
          202.79999999999998
        ],
        "WEST_PENALTY_SE": [
          897.5999999999999,
          708.0
        ],
        "WEST_GOAL_AREA_NW": [
          126.0,
          304.8
        ],
        "WEST_GOAL_AREA_NE": [
          391.2,
          303.59999999999997
        ],
        "WEST_GOAL_AREA_SE": [
          271.2,
          524.4
        ],
        "WEST_PENALTY_SPOT": [
          628.8,
          400.79999999999995
        ],
        "WEST_GOAL_CENTER": [
          48.0,
          402.0
        ]
      },
      "world_points": {
        "NW_CORNER": [
          -52.5,
          34.0
        ],
        "WEST_PENALTY_NW": [
          -52.5,
          20.16
        ],
        "WEST_PENALTY_NE": [
          -36.0,
          20.16
        ],
        "WEST_PENALTY_SE": [
          -36.0,
          -20.16
        ],
        "WEST_GOAL_AREA_NW": [
          -52.5,
          9.16
        ],
        "WEST_GOAL_AREA_NE": [
          -47.0,
          9.16
        ],
        "WEST_GOAL_AREA_SE": [
          -47.0,
          -9.16
        ],
        "WEST_PENALTY_SPOT": [
          -41.5,
          0.0
        ],
        "WEST_GOAL_CENTER": [
          -52.5,
          0.0
        ]
      },
      "homography_image_to_world": [
        [
          0.028473386173465332,
          -0.04634326975149063,
          -63.37345616020338
        ],
        [
          -9.200727708392182e-05,
          -0.1294645024050692,
          52.201433584195165
        ],
        [
          1.5592317551404523e-05,
          0.001332617576561472,
          0.9999999999999999
        ]
      ],
      "reprojection_errors_m": {
        "NW_CORNER": 0.06247131761393068,
        "WEST_PENALTY_NW": 0.0524487513982108,
        "WEST_PENALTY_NE": 0.05951201215643355,
        "WEST_PENALTY_SE": 0.08987788257022918,
        "WEST_GOAL_AREA_NW": 0.12097999413148175,
        "WEST_GOAL_AREA_NE": 0.04386561977795685,
        "WEST_GOAL_AREA_SE": 0.0854868880573427,
        "WEST_PENALTY_SPOT": 0.16570426758578508,
        "WEST_GOAL_CENTER": 0.10071390545933707
      },
      "reprojection_rmse_m": 0.09412922858801165
    },
    "6": {
      "camera_id": 6,
      "image_path": "/ssd/ISSIA-Soccer/Annotation/Reference-Camera-6.bmp",
      "field_length_m": 105.0,
      "field_width_m": 68.0,
      "world_coordinate_system": {
        "origin": "field_center",
        "x_axis": "east_positive_long_axis",
        "y_axis": "north_positive_short_axis",
        "units": "meters"
      },
      "image_points": {
        "SW_CORNER": [
          1641.6,
          115.19999999999999
        ],
        "WEST_PENALTY_NE": [
          1023.5999999999999,
          703.1999999999999
        ],
        "WEST_PENALTY_SE": [
          1003.1999999999999,
          208.79999999999998
        ],
        "WEST_PENALTY_SW": [
          1717.1999999999998,
          207.6
        ],
        "WEST_GOAL_AREA_NE": [
          1652.3999999999999,
          523.1999999999999
        ],
        "WEST_GOAL_AREA_SE": [
          1534.8,
          303.59999999999997
        ],
        "WEST_GOAL_AREA_SW": [
          1798.8,
          303.59999999999997
        ],
        "WEST_PENALTY_SPOT": [
          1299.6,
          403.2
        ],
        "WEST_GOAL_CENTER": [
          1879.1999999999998,
          405.59999999999997
        ]
      },
      "world_points": {
        "SW_CORNER": [
          -52.5,
          -34.0
        ],
        "WEST_PENALTY_NE": [
          -36.0,
          20.16
        ],
        "WEST_PENALTY_SE": [
          -36.0,
          -20.16
        ],
        "WEST_PENALTY_SW": [
          -52.5,
          -20.16
        ],
        "WEST_GOAL_AREA_NE": [
          -47.0,
          9.16
        ],
        "WEST_GOAL_AREA_SE": [
          -47.0,
          -9.16
        ],
        "WEST_GOAL_AREA_SW": [
          -52.5,
          -9.16
        ],
        "WEST_PENALTY_SPOT": [
          -41.5,
          0.0
        ],
        "WEST_GOAL_CENTER": [
          -52.5,
          0.0
        ]
      },
      "homography_image_to_world": [
        [
          -0.03310725800497133,
          -0.05879569075964642,
          -3.5104457426962243
        ],
        [
          -0.0005789643001926563,
          0.1444094606240331,
          -57.172391865676474
        ],
        [
          2.3971523760561666e-05,
          0.0016395773777489247,
          1.0
        ]
      ],
      "reprojection_errors_m": {
        "SW_CORNER": 0.25379463635241334,
        "WEST_PENALTY_NE": 0.17111734972992718,
        "WEST_PENALTY_SE": 0.14451629907073701,
        "WEST_PENALTY_SW": 0.24422736525668495,
        "WEST_GOAL_AREA_NE": 0.10848878060576234,
        "WEST_GOAL_AREA_SE": 0.11009915071753289,
        "WEST_GOAL_AREA_SW": 0.16684299111435535,
        "WEST_PENALTY_SPOT": 0.17815420436504542,
        "WEST_GOAL_CENTER": 0.21835777996530525
      },
      "reprojection_rmse_m": 0.18420160882743067
    }
  },
  "field_length_m": 105.0,
  "field_width_m": 68.0,
  "world_coordinate_system": {
    "origin": "field_center",
    "x_axis": "east_positive_long_axis",
    "y_axis": "north_positive_short_axis",
    "units": "meters"
  }
}